ace/__init__.py
ace/core/__init__.py
ace/core/control.py
ace/core/limiters.py
ace/core/logger.py
ace/core/signals.py
ace/integrations/__init__.py
ace/integrations/asyncio_integration.py
ace/integrations/kafka_integration.py
ace/integrations/threadpool_integration.py
ace_concurrency-0.1.1.dist-info/licenses/LICENSE
ace_concurrency-0.1.1.dist-info/METADATA
ace_concurrency-0.1.1.dist-info/WHEEL
ace_concurrency-0.1.1.dist-info/top_level.txt
ace_concurrency-0.1.1.dist-info/RECORD
