Metadata-Version: 2.4
Name: ace-concurrency
Version: 0.1.1
Summary: AIMD-based adaptive throttling for asyncio, thread pools, and Kafka consumers — like a semaphore with a brain.
Author: Aryan Inguz
Author-email: Aryan Inguz <aryaninguz369@gmail.com>
License: MIT
Keywords: asyncio,threads,kafka,concurrency,aimd,backpressure
Classifier: Programming Language :: Python :: 3
Classifier: License :: OSI Approved :: MIT License
Classifier: Operating System :: OS Independent
Requires-Python: >=3.8
License-File: LICENSE
Requires-Dist: psutil>=5.9.0
Requires-Dist: kafka-python>=2.0.2
Dynamic: author
Dynamic: license-file
Dynamic: requires-python
